{
  "kind": "collectionType",
  "collectionName": "visitors",
  "info": {
    "singularName": "visitor",
    "pluralName": "visitors",
    "displayName": "Visitor"
  },
  "options": {
    "draftAndPublish": true
  },
  "pluginOptions": {},
  "attributes": {
    "name": {
      "type": "string"
    },
    "surname": {
      "type": "string"
    },
    "patronymic": {
      "type": "string"
    },
    "address": {
      "type": "string"
    },
    "phone": {
      "type": "string"
    },
    "birth": {
      "type": "string"
    },
    "bonus": {
      "type": "integer"
    },
    "moderated": {
      "type": "boolean"
    }
  }
}
